pyrbtree/__init__.py
pyrbtree/_rbtree.pyd
pyrbtree/rbtree.py
pyrbtree/version.py
pyrbtree-0.6.1.dist-info/LICENSE.txt
pyrbtree-0.6.1.dist-info/METADATA
pyrbtree-0.6.1.dist-info/WHEEL
pyrbtree-0.6.1.dist-info/top_level.txt
pyrbtree-0.6.1.dist-info/RECORD
