Metadata-Version: 2.1
Name: pyrbtree
Version: 0.6.1
Summary: Red Black tree extension package
Author-email: SBA <s-ball@laposte.net>
Project-URL: Homepage, https://github.com/s-ball/pyrbtree
Project-URL: Bug Tracker, https://github.com/s-ball/pyrbtree/issues
Classifier: Programming Language :: Python :: 3
Classifier: License :: OSI Approved :: MIT License
Classifier: Operating System :: OS Independent
Classifier: Development Status :: 3 - Alpha
Classifier: Intended Audience :: Developers
Classifier: Programming Language :: C
Requires-Python: >=3.7
License-File: LICENSE.txt
